kitoolz/__init__.py
kitoolz/__version__.py
kitoolz/_signatures.py
kitoolz/_version.py
kitoolz/compatibility.py
kitoolz/dicttoolz.py
kitoolz/functoolz.py
kitoolz/itertoolz.py
kitoolz/recipes.py
kitoolz/utils.py
kitoolz/curried/__init__.py
kitoolz/curried/exceptions.py
kitoolz/curried/operator.py
kitoolz/sandbox/__init__.py
kitoolz/sandbox/core.py
kitoolz/sandbox/parallel.py
kitoolz/tests/test_compatibility.py
kitoolz/tests/test_curried.py
kitoolz/tests/test_curried_doctests.py
kitoolz/tests/test_dicttoolz.py
kitoolz/tests/test_functoolz.py
kitoolz/tests/test_inspect_args.py
kitoolz/tests/test_itertoolz.py
kitoolz/tests/test_recipes.py
kitoolz/tests/test_serialization.py
kitoolz/tests/test_signatures.py
kitoolz/tests/test_tlz.py
kitoolz/tests/test_utils.py
tlz/__init__.py
tlz/_build_tlz.py
kitoolz-0.1.2.dist-info/AUTHORS.md
kitoolz-0.1.2.dist-info/LICENSE.txt
kitoolz-0.1.2.dist-info/METADATA
kitoolz-0.1.2.dist-info/WHEEL
kitoolz-0.1.2.dist-info/top_level.txt
kitoolz-0.1.2.dist-info/RECORD
